pyhypergeomatrix/__init__.py
pyhypergeomatrix/hypergeomat.py
pyhypergeomatrix-0.1.0.dist-info/LICENSE
pyhypergeomatrix-0.1.0.dist-info/METADATA
pyhypergeomatrix-0.1.0.dist-info/WHEEL
pyhypergeomatrix-0.1.0.dist-info/RECORD
